twitterag/__init__.py
twitterag/__main__.py
twitterag/config_tools.py
twitterag/likes.py
twitterag/tweet_lookup.py
twitterag/tweet_timeline.py
twitterag/user_follows.py
twitterag/user_profile.py
twitterag/exceptions/__init__.py
twitterag/exceptions/auth_except.py
Twitter_Aggregate_Generator-1.2.0.dist-info/METADATA
Twitter_Aggregate_Generator-1.2.0.dist-info/WHEEL
Twitter_Aggregate_Generator-1.2.0.dist-info/top_level.txt
Twitter_Aggregate_Generator-1.2.0.dist-info/RECORD
