Metadata-Version: 2.1
Name: Twitter-Aggregate-Generator
Version: 1.2.0
Author-email: Branden Kunkel <kunkel.branden6130@gmail.com>
Project-URL: homepage, https://github.com/Branden-Kunkel/twitter_aggregate_generator
Classifier: Development Status :: 4 - Beta
Classifier: Intended Audience :: Science/Research
Classifier: Intended Audience :: Education
Classifier: Intended Audience :: Developers
Classifier: License :: OSI Approved :: GNU General Public License v3 (GPLv3)
Classifier: Natural Language :: English
Classifier: Operating System :: POSIX :: Linux
Classifier: Programming Language :: Python :: 3.8
Requires-Python: >=3.8
Requires-Dist: requests (==2.28.1)
